cpucopy0/BUS/regfile.v
/******头文件******/
`include"regfile.h"

/******模块******/
module regfile(
	/******时钟和复位******/
	input	wire		clk,
	input	wire		reset_,
	
	/******访问接口******/
	input  wire [`AddrBus]	addr,
	input  wire [`DataBus]	d_in,
	inout  wire [`DataBus]	Bus,
	input  wire 		we_,
	input  wire 		as_,
	input  wire		cs_,
	output reg		rdy_
);
	
	/******内部信号******/
	reg	[`DataBus]	ff[`DATA_D-1:0];
	reg	[`DataBus]	d_out;
	integer			i;

//	assign Bus = (we_ == `ENABLE_)?	   d_in:{`DATA_W{1'bz}};
	assign Bus = (1)?   d_out:{`DATA_W{1'bz}};
	
	/******读取访问******/
	always @(negedge clk or negedge reset_)
		if(reset_ == 0)
			d_out = #1 {`DATA_W{1'b0}};
		else 
			d_out = #1 ff[addr];
	
	/******写入访问******/
	always @(posedge clk or negedge reset_)
		if(reset_ == 0)
			ff[i] <= #1 {`DATA_W{1'b0}};
		else if(we_ ==`ENABLE_)
			ff[addr] <= #1 d_in;
	
	/******生成rdy_信号****/					
	always @(posedge clk or negedge reset_)
	if(reset_ == 0)
		rdy_	<= #1 `DISABLE_;
	else if((cs_== `ENABLE_)&&(as_ == `ENABLE_))
		rdy_	<= #1 `ENABLE_;
	else	
		rdy_	<= #1 `DISABLE_;

endmodule

cpu试验品/bus_slave_mux.v
//****************总线从属多路复用器
`include "header/bus.h"
module bus_slave_mux(
	input wire		s0_cs_,			//片选
	input wire	[31:0]	s0_rd_data,		//读出的数据
	input wire		s0_rdy_,		//就绪

	input wire		s1_cs_,
	input wire	[31:0]	s1_rd_data,
	input wire		s1_rdy_,
	input wire		s2_cs_,
	input wire	[31:0]	s2_rd_data,
	input wire		s2_rdy_,
	input wire		s3_cs_,
	input wire	[31:0]	s3_rd_data,
	input wire		s3_rdy_,
	input wire		s4_cs_,
	input wire	[31:0]	s4_rd_data,
	input wire		s4_rdy_,
	input wire		s5_cs_,
	input wire	[31:0]	s5_rd_data,
	input wire		s5_rdy_,
	input wire		s6_cs_,
	input wire	[31:0]	s6_rd_data,
	input wire		s6_rdy_,
	input wire		s7_cs_,
	input wire	[31:0]	s7_rd_data,
	input wire		s7_rdy_,

	output reg	[31:0]	m_rd_data,		//选出信号
	output reg		m_rdy_
);
	always @ * 
		if(s0_cs_ == `ENABLE_) begin
			m_rd_data = s0_rd_data;
			m_rdy_	  = s0_rdy_;
		end else if(s1_cs_ == `ENABLE_) begin
			m_rd_data = s1_rd_data;
			m_rdy_	  = s1_rdy_;
		end else if(s2_cs_ == `ENABLE_) begin
			m_rd_data = s2_rd_data;
			m_rdy_	  = s2_rdy_;
		end else if(s3_cs_ == `ENABLE_) begin
			m_rd_data = s3_rd_data;
			m_rdy_	  = s3_rdy_;
		end else if(s4_cs_ == `ENABLE_) begin
			m_rd_data = s4_rd_data;
			m_rdy_	  = s4_rdy_;
		end else if(s5_cs_ == `ENABLE_) begin
			m_rd_data = s5_rd_data;
			m_rdy_	  = s5_rdy_;
		end else if(s6_cs_ == `ENABLE_) begin
			m_rd_data = s6_rd_data;
			m_rdy_	  = s6_rdy_;
		end else if(s7_cs_ == `ENABLE_) begin
			m_rd_data = s7_rd_data;
			m_rdy_	  = s7_rdy_;
		end else begin
			m_rd_data = `WORD_DATA_W'h0;
			m_rdy_    = `DISABLE_;
		end

endmodule

cpucopy0/BUS/bus_addr_dec.v
//************************地址译码器

`include "header/firstglobal.h"
`include "header/bus.h"
module bus_addr_dec(
	input wire	[`WordAddrBus]	s_addr,
	output reg		s0_cs_,		//片选
	output reg		s1_cs_,
	output reg		s2_cs_,
	output reg		s3_cs_,
	output reg		s4_cs_,
	output reg		s5_cs_,
	output reg		s6_cs_,
	output reg		s7_cs_
	
);
	
	/*************总线从属索引***************/
	wire	[`BusSlaveIndexBus] s_index = s_addr[`BusSlaveIndexLoc];
	
	/*************总线从属多路复用器*********/
	always @ * begin				
		s0_cs_ = `DISABLE_;
		s1_cs_ = `DISABLE_;
		s2_cs_ = `DISABLE_;
		s3_cs_ = `DISABLE_;
		s4_cs_ = `DISABLE_;
		s5_cs_ = `DISABLE_;
		s6_cs_ = `DISABLE_;
		s7_cs_ = `DISABLE_;
		case (s_index)
			`BUS_SLAVE_0 : s0_cs_ = `ENABLE_;
			`BUS_SLAVE_1 : s1_cs_ = `ENABLE_;
			`BUS_SLAVE_2 : s2_cs_ = `ENABLE_;
			`BUS_SLAVE_3 : s3_cs_ = `ENABLE_;
			`BUS_SLAVE_4 : s4_cs_ = `ENABLE_;
			`BUS_SLAVE_5 : s5_cs_ = `ENABLE_;
			`BUS_SLAVE_6 : s6_cs_ = `ENABLE_;
			`BUS_SLAVE_7 : s7_cs_ = `ENABLE_;
		endcase
	end

endmodule

cpu试验品/bus_master_mux.v
//*******************根据mx_grnt_选择仲裁后所有者的控制，地址，数据
`include "header/bus.h"
module bus_master_mux(
	input wire	[29:0]	m0_addr,		//地址
	input wire		m0_as_,			//地址选通
	input wire		m0_rw,			//读写
	input wire	[31:0]	m0_wr_data,		//写入的数据
	input wire		m0_grnt_,  		//赋予总线

	input wire	[29:0]	m1_addr,		//地址
	input wire		m1_as_,			//地址选通
	input wire		m1_rw,			//读写
	input wire	[31:0]	m1_wr_data,		//写入的数据
	input wire		m1_grnt_,  		//赋予总线

	input wire	[29:0]	m2_addr,		//地址
	input wire		m2_as_,			//地址选通
	input wire		m2_rw,			//读写
	input wire	[31:0]	m2_wr_data,		//写入的数据
	input wire		m2_grnt_,  		//赋予总线

	input wire	[29:0]	m3_addr,		//地址
	input wire		m3_as_,			//地址选通
	input wire		m3_rw,			//读写
	input wire	[31:0]	m3_wr_data,		//写入的数据
	input wire		m3_grnt_,  		//赋予总线

	//**********************共享信号总线从属，输出选通信号
	output reg	[29:0]	s_addr,
	output reg 		s_as_,
	output reg		s_rw,
	output reg	[31:0]	s_wr_data
);
	
	always @ * 
		if(m0_grnt_ ==`ENABLE_) begin
			s_addr		= m0_addr;
			s_as_		= m0_as_;
			s_rw		= m0_rw;
			s_wr_data	= m0_wr_data;
		end else if (m1_grnt_ == `ENABLE_) begin
			s_addr		= m1_addr;
			s_as_		= m1_as_;
			s_rw		= m1_rw;
			s_wr_data	= m1_wr_data;
		end else if (m2_grnt_ == `ENABLE_) begin
			s_addr		= m2_addr;
			s_as_		= m2_as_;
			s_rw		= m2_rw;
			s_wr_data	= m2_wr_data;
		end else if (m3_grnt_ == `ENABLE_) begin
			s_addr		= m3_addr;
			s_as_		= m3_as_;
			s_rw		= m3_rw;
			s_wr_data	= m3_wr_data;
		end

endmodule

cpu试验品/BUS/bus_arbiter.v
//待优化项目：1.合并always   2.加入默认else，避免锁存器

//********************************总线仲裁
`include "header/bus.h"
module bus_arbiter(
	input	 wire		clk,
	input	 wire		reset,
	
	//**************0号总线主控
	input	 wire		m0_req_,		//请求总线
	output	 reg		m0_grnt_,		//赋予总线

	input	 wire		m1_req_,
	output	 reg		m1_grnt_,
	input	 wire		m2_req_,
	output	 reg		m2_grnt_,
	input	 wire		m3_req_,
	output	 reg		m3_grnt_
);
	reg	[1:0]	owner;				//总线所有者
	
	//******************************赋予总线使用权
	always @ * begin
		//****赋予总线使用权初始化
		m0_grnt_ = `DISABLE_;
		m1_grnt_ = `DISABLE_;
		m2_grnt_ = `DISABLE_;
		m3_grnt_ = `DISABLE_;
		//****赋予总线使用权
		case (owner)
			`BUS_OWNER_MASTER_0 :	m0_grnt_ = `ENABLE_;

			`BUS_OWNER_MASTER_1 :	m1_grnt_ = `ENABLE_;

			`BUS_OWNER_MASTER_2 :	m2_grnt_ = `ENABLE_;

			`BUS_OWNER_MASTER_3 :	m3_grnt_ = `ENABLE_;
		endcase
	end

	always @(posedge clk or `RESET_EDGE reset) 
		if(reset == `RESET_ENABLE) 
			owner <= #1 `BUS_OWNER_MASTER_0;		//开机等于复位？
		else 
			case (owner)
			`BUS_OWNER_MASTER_0 : 				//所有权级别：0>1>2>3
				if	(m0_req_ == `ENABLE_)	 owner	<= #1 `BUS_OWNER_MASTER_0;
				else if (m1_req_ == `ENABLE_)	 owner	<= #1 `BUS_OWNER_MASTER_1;
				else if (m2_req_ == `ENABLE_)	 owner	<= #1 `BUS_OWNER_MASTER_2;
				else if (m3_req_ == `ENABLE_)	 owner	<= #1 `BUS_OWNER_MASTER_3;
				//**********注意此处不直接 m0_grnt_ <= #1 `ENABLE_是因为两者always语句
				//**********的判断条件不一样，而m0_grnt又不能在两种always里赋值，必须
				//**********借助辅助的中间量。
			
			`BUS_OWNER_MASTER_1 :
				if	(m1_req_ == `ENABLE_)	 owner	<= #1 `BUS_OWNER_MASTER_1;
				else if (m2_req_ == `ENABLE_)	 owner	<= #1 `BUS_OWNER_MASTER_2;
				else if (m3_req_ == `ENABLE_)	 owner	<= #1 `BUS_OWNER_MASTER_3;
				else if (m0_req_ == `ENABLE_)	 owner	<= #1 `BUS_OWNER_MASTER_0;

			`BUS_OWNER_MASTER_2 :
				if	(m2_req_ == `ENABLE_)	 owner	<= #1 `BUS_OWNER_MASTER_2;
				else if (m3_req_ == `ENABLE_)	 owner	<= #1 `BUS_OWNER_MASTER_3;
				else if (m0_req_ == `ENABLE_)	 owner	<= #1 `BUS_OWNER_MASTER_0;
				else if (m1_req_ == `ENABLE_)	 owner	<= #1 `BUS_OWNER_MASTER_1;
							
			`BUS_OWNER_MASTER_3 :
				if	(m3_req_ == `ENABLE_)	 owner	<= #1 `BUS_OWNER_MASTER_3;
				else if (m0_req_ == `ENABLE_)	 owner	<= #1 `BUS_OWNER_MASTER_0;
				else if (m1_req_ == `ENABLE_)	 owner	<= #1 `BUS_OWNER_MASTER_1;
				else if (m2_req_ == `ENABLE_)	 owner	<= #1 `BUS_OWNER_MASTER_2;
		endcase
endmodule

cpu试验品/BUS/bus_top_test.v
//***采用独热码编码方式，减少译码的信号延迟。提高速度。
//***代码编写时简化相同条目如：m0,m1->m[1:0].                  待做
//***s_addr 输出可以作为内部连线来使用？
`include "header/bus.h"
module bus_top_test;
	//*************时钟，复位
	reg 		clk;
	reg		reset;
	
	//*************主控独立信号
	reg		m0_req_;
	reg		m1_req_;
	reg		m2_req_;
	reg		m3_req_;
	wire		m0_grnt_;		//输出的目的是告知cpu仲裁通过，可以使用总线了。
	wire		m1_grnt_;
	wire		m2_grnt_;
	wire 		m3_grnt_;

	reg	[29:0]	m0_addr;
	reg		m0_as_;
	reg		m0_rw;
	reg	[31:0]	m0_wr_data;
	reg	[29:0]	m1_addr;
	reg		m1_as_;
	reg		m1_rw;
	reg	[31:0]	m1_wr_data;
	reg	[29:0]	m2_addr;
	reg		m2_as_;
	reg		m2_rw;
	reg	[31:0]	m2_wr_data;
	reg	[29:0]	m3_addr;
	reg		m3_as_;
	reg		m3_rw;
	reg	[31:0]	m3_wr_data;

	//*************************地址译码器输出从属选择信号(相对于把从属内部译码器拿出来）
	wire		s0_cs_;		//****片选cs与as地址选通信号共同决定从属rdy信号
	wire		s1_cs_;
	wire		s2_cs_;
	wire		s3_cs_;
	wire		s4_cs_;
	wire		s5_cs_;
	wire		s6_cs_;
	wire		s7_cs_;

	//*************************总线从属共享信号（控制相应从属）
	wire	[29:0] 	s_addr;
	wire		s_as_;
	wire		s_rw;
	wire	[31:0]	s_wr_data;
	
	//*************************总线从属独立信号（得到从属应答信号）
	wire	[31:0]	s0_rd_data;
	wire		s0_rdy_;
	wire	[31:0]	s1_rd_data;
	wire		s1_rdy_;
	wire	[31:0]	s2_rd_data;
	wire		s2_rdy_;
	wire	[31:0]	s3_rd_data;
	wire		s3_rdy_;
	wire	[31:0]	s4_rd_data;
	wire		s4_rdy_;
	wire	[31:0]	s5_rd_data;
	wire		s5_rdy_;
	wire	[31:0]	s6_rd_data;
	wire		s6_rdy_;
	wire	[31:0]	s7_rd_data;
	wire		s7_rdy_;
	
	//*************************总线主控共享信号
	wire	[31:0]	m_rd_data;
	wire		m_rdy_;


	bus_arbiter	bus_arbiter0	(.clk(clk),.reset(reset),
					 .m0_req_ (m0_req_),
					 .m0_grnt_(m0_grnt_),
					 .m1_req_ (m1_req_),
					 .m1_grnt_(m1_grnt_),
					 .m2_req_ (m2_req_),
					 .m2_grnt_(m2_grnt_),
					 .m3_req_ (m3_req_),
					 .m3_grnt_(m3_grnt_)
					);
	bus_master_mux	bus_master_mux0	(.m0_addr(m0_addr),.m0_as_(m0_as_),.m0_rw(m0_rw),.m0_wr_data(m0_wr_data),.m0_grnt_(m0_grnt_),
					 .m1_addr(m1_addr),.m1_as_(m1_as_),.m1_rw(m1_rw),.m1_wr_data(m1_wr_data),.m1_grnt_(m1_grnt_),
					 .m2_addr(m2_addr),.m2_as_(m2_as_),.m2_rw(m2_rw),.m2_wr_data(m2_wr_data),.m2_grnt_(m2_grnt_),
					 .m3_addr(m3_addr),.m3_as_(m3_as_),.m3_rw(m3_rw),.m3_wr_data(m3_wr_data),.m3_grnt_(m3_grnt_),
					 .s_addr(s_addr),.s_as_(s_as_),.s_rw(s_rw),.s_wr_data(s_wr_data)
					);
	bus_addr_dec	bus_addr_dec0	(.s_addr(s_addr),.s0_cs_(s0_cs_),
							 .s1_cs_(s1_cs_),
							 .s2_cs_(s2_cs_),
							 .s3_cs_(s3_cs_),
							 .s4_cs_(s4_cs_),
							 .s5_cs_(s5_cs_),
							 .s6_cs_(s6_cs_),
							 .s7_cs_(s7_cs_)
					);
	bus_slave_mux	bus_slave_mux0	(.s0_cs_(s0_cs_),.s0_rd_data(s0_rd_data),.s0_rdy_(s0_rdy_),
					 .s1_cs_(s1_cs_),.s1_rd_data(s1_rd_data),.s1_rdy_(s1_rdy_),
					 .s2_cs_(s2_cs_),.s2_rd_data(s2_rd_data),.s2_rdy_(s2_rdy_),
					 .s3_cs_(s3_cs_),.s3_rd_data(s3_rd_data),.s3_rdy_(s3_rdy_),
					 .s4_cs_(s4_cs_),.s4_rd_data(s4_rd_data),.s4_rdy_(s4_rdy_),
					 .s5_cs_(s5_cs_),.s5_rd_data(s5_rd_data),.s5_rdy_(s5_rdy_),
					 .s6_cs_(s6_cs_),.s6_rd_data(s6_rd_data),.s6_rdy_(s6_rdy_),
					 .s7_cs_(s7_cs_),.s7_rd_data(s7_rd_data),.s7_rdy_(s7_rdy_),
					 .m_rd_data(m_rd_data),.m_rdy_(m_rdy_)
					);
	 regfile 	regfile0	(
		/******时钟和复位******/
			.clk(clk),
			.reset_(reset),
		
		/******访问接口******/
			.addr(s_addr),
			.d_in(s_wr_data),
			.Bus(s0_rd_data),
			.we_(s_rw),
	 		.as_(s_as_),
			.cs_(s0_cs_),
			.rdy_(s0_rdy_)
	);

	always #50 clk = ~clk;
	initial begin
		#0	clk=1;reset=0;
		#100	reset	=1;
			m0_req_ = `ENABLE_;
			m0_addr = 30'd0;
			m0_rw	= 0;
			m0_as_	= `ENABLE_;
			m0_wr_data = 32'd22;
		#100
		#100	m0_req_ = `ENABLE_;
			m0_addr = 30'd1;
			m0_rw	= 1;
			m0_as_	= `ENABLE_;
			m0_wr_data = 32'd33;	 
		#200	m0_req_ = `ENABLE_;
			m0_addr = 30'd0;
			m0_rw	= 1;
			m0_as_	= `ENABLE_;
			m0_wr_data = 32'd33;
		#200	$finish;
	end
	
	initial begin
		$dumpfile("bus_top_test.vcd");
		$dumpvars(0,bus_top_test);
	end
			
					 
endmodule

cpucopy0/BUS/bus_top_test.vcd
$date
	Mon Jul 11 17:53:32 2016
$end
$version
	Icarus Verilog
$end
$timescale
	1s
$end
$scope module bus_top_test $end
$var wire 32 ! s1_rd_data [31:0] $end
$var wire 1 " s1_rdy_ $end
$var wire 32 # s2_rd_data [31:0] $end
$var wire 1 $ s2_rdy_ $end
$var wire 32 % s3_rd_data [31:0] $end
$var wire 1 & s3_rdy_ $end
$var wire 32 ' s4_rd_data [31:0] $end
$var wire 1 ( s4_rdy_ $end
$var wire 32 ) s5_rd_data [31:0] $end
$var wire 1 * s5_rdy_ $end
$var wire 32 + s6_rd_data [31:0] $end
$var wire 1 , s6_rdy_ $end
$var wire 32 - s7_rd_data [31:0] $end
$var wire 1 . s7_rdy_ $end
$var wire 32 / s_wr_data [31:0] $end
$var wire 1 0 s_rw $end
$var wire 1 1 s_as_ $end
$var wire 30 2 s_addr [29:0] $end
$var wire 1 3 s7_cs_ $end
$var wire 1 4 s6_cs_ $end
$var wire 1 5 s5_cs_ $end
$var wire 1 6 s4_cs_ $end
$var wire 1 7 s3_cs_ $end
$var wire 1 8 s2_cs_ $end
$var wire 1 9 s1_cs_ $end
$var wire 1 : s0_rdy_ $end
$var wire 32 ; s0_rd_data [31:0] $end
$var wire 1 < s0_cs_ $end
$var wire 1 = m_rdy_ $end
$var wire 32 > m_rd_data [31:0] $end
$var wire 1 ? m3_grnt_ $end
$var wire 1 @ m2_grnt_ $end
$var wire 1 A m1_grnt_ $end
$var wire 1 B m0_grnt_ $end
$var reg 1 C clk $end
$var reg 30 D m0_addr [29:0] $end
$var reg 1 E m0_as_ $end
$var reg 1 F m0_req_ $end
$var reg 1 G m0_rw $end
$var reg 32 H m0_wr_data [31:0] $end
$var reg 30 I m1_addr [29:0] $end
$var reg 1 J m1_as_ $end
$var reg 1 K m1_req_ $end
$var reg 1 L m1_rw $end
$var reg 32 M m1_wr_data [31:0] $end
$var reg 30 N m2_addr [29:0] $end
$var reg 1 O m2_as_ $end
$var reg 1 P m2_req_ $end
$var reg 1 Q m2_rw $end
$var reg 32 R m2_wr_data [31:0] $end
$var reg 30 S m3_addr [29:0] $end
$var reg 1 T m3_as_ $end
$var reg 1 U m3_req_ $end
$var reg 1 V m3_rw $end
$var reg 32 W m3_wr_data [31:0] $end
$var reg 1 X reset $end
$scope module bus_addr_dec0 $end
$var wire 3 Y s_index [2:0] $end
$var wire 30 Z s_addr [29:0] $end
$var reg 1 < s0_cs_ $end
$var reg 1 9 s1_cs_ $end
$var reg 1 8 s2_cs_ $end
$var reg 1 7 s3_cs_ $end
$var reg 1 6 s4_cs_ $end
$var reg 1 5 s5_cs_ $end
$var reg 1 4 s6_cs_ $end
$var reg 1 3 s7_cs_ $end
$upscope $end
$scope module bus_arbiter0 $end
$var wire 1 C clk $end
$var wire 1 F m0_req_ $end
$var wire 1 K m1_req_ $end
$var wire 1 P m2_req_ $end
$var wire 1 U m3_req_ $end
$var wire 1 X reset $end
$var reg 1 B m0_grnt_ $end
$var reg 1 A m1_grnt_ $end
$var reg 1 @ m2_grnt_ $end
$var reg 1 ? m3_grnt_ $end
$var reg 2 [ owner [1:0] $end
$upscope $end
$scope module bus_master_mux0 $end
$var wire 30 \ m0_addr [29:0] $end
$var wire 1 E m0_as_ $end
$var wire 1 B m0_grnt_ $end
$var wire 1 G m0_rw $end
$var wire 32 ] m0_wr_data [31:0] $end
$var wire 30 ^ m1_addr [29:0] $end
$var wire 1 J m1_as_ $end
$var wire 1 A m1_grnt_ $end
$var wire 1 L m1_rw $end
$var wire 32 _ m1_wr_data [31:0] $end
$var wire 30 ` m2_addr [29:0] $end
$var wire 1 O m2_as_ $end
$var wire 1 @ m2_grnt_ $end
$var wire 1 Q m2_rw $end
$var wire 32 a m2_wr_data [31:0] $end
$var wire 30 b m3_addr [29:0] $end
$var wire 1 T m3_as_ $end
$var wire 1 ? m3_grnt_ $end
$var wire 1 V m3_rw $end
$var wire 32 c m3_wr_data [31:0] $end
$var reg 30 d s_addr [29:0] $end
$var reg 1 1 s_as_ $end
$var reg 1 0 s_rw $end
$var reg 32 e s_wr_data [31:0] $end
$upscope $end
$scope module bus_slave_mux0 $end
$var wire 1 < s0_cs_ $end
$var wire 1 9 s1_cs_ $end
$var wire 32 f s1_rd_data [31:0] $end
$var wire 1 " s1_rdy_ $end
$var wire 1 8 s2_cs_ $end
$var wire 32 g s2_rd_data [31:0] $end
$var wire 1 $ s2_rdy_ $end
$var wire 1 7 s3_cs_ $end
$var wire 32 h s3_rd_data [31:0] $end
$var wire 1 & s3_rdy_ $end
$var wire 1 6 s4_cs_ $end
$var wire 32 i s4_rd_data [31:0] $end
$var wire 1 ( s4_rdy_ $end
$var wire 1 5 s5_cs_ $end
$var wire 32 j s5_rd_data [31:0] $end
$var wire 1 * s5_rdy_ $end
$var wire 1 4 s6_cs_ $end
$var wire 32 k s6_rd_data [31:0] $end
$var wire 1 , s6_rdy_ $end
$var wire 1 3 s7_cs_ $end
$var wire 32 l s7_rd_data [31:0] $end
$var wire 1 . s7_rdy_ $end
$var wire 1 : s0_rdy_ $end
$var wire 32 m s0_rd_data [31:0] $end
$var reg 32 n m_rd_data [31:0] $end
$var reg 1 = m_rdy_ $end
$upscope $end
$scope module regfile0 $end
$var wire 32 o Bus [31:0] $end
$var wire 30 p addr [29:0] $end
$var wire 1 1 as_ $end
$var wire 1 C clk $end
$var wire 1 < cs_ $end
$var wire 32 q d_in [31:0] $end
$var wire 1 X reset_ $end
$var wire 1 0 we_ $end
$var reg 32 r d_out [31:0] $end
$var reg 1 : rdy_ $end
$var integer 32 s i [31:0] $end
$upscope $end
$upscope $end
$enddefinitions $end
#0
$dumpvars
bx s
bx r
bx q
bx p
bx o
b0 n
bx m
bz l
bz k
bz j
bz i
bz h
bz g
bz f
bx e
bx d
bx c
bx b
bx a
bx `
bx _
bx ^
bx ]
bx \
bx [
bx Z
bx Y
0X
bx W
xV
xU
xT
bx S
bx R
xQ
xP
xO
bx N
bx M
xL
xK
xJ
bx I
bx H
xG
xF
xE
bx D
1C
xB
xA
x@
x?
b0 >
0=
x<
bx ;
x:
x9
x8
x7
x6
x5
x4
x3
bx 2
x1
x0
bx /
z.
bz -
z,
bz +
z*
bz )
z(
bz '
z&
bz %
z$
bz #
z"
bz !
$end
#1
1?
1@
1A
0B
b0 [
1:
b0 ;
b0 m
b0 o
b0 r
#50
0C
#100
1=
13
14
15
16
17
18
19
0<
b0 Y
b10110 /
b10110 e
b10110 q
00
01
b0 2
b0 Z
b0 d
b0 p
1C
b10110 H
b10110 ]
0E
0G
b0 D
b0 \
0F
1X
#150
0C
#151
b10110 >
b10110 n
b10110 ;
b10110 m
b10110 o
b10110 r
#200
1C
#201
0=
0:
#250
0C
#300
b100001 /
b100001 e
b100001 q
10
b1 2
b1 Z
b1 d
b1 p
1C
b100001 H
b100001 ]
1G
b1 D
b1 \
#350
0C
#351
bx >
bx n
bx ;
bx m
bx o
bx r
#400
1C
#450
0C
#500
b0 2
b0 Z
b0 d
b0 p
1C
b0 D
b0 \
#550
0C
#551
b10110 >
b10110 n
b10110 ;
b10110 m
b10110 o
b10110 r
