cpuother/regfile/regfile.v
/******头文件******/
`include"regfile.h"

/******模块******/
module regfile(
	/******时钟和复位******/
	input	wire		clk,
	input	wire		reset_,
	
	/******访问接口******/
	input  wire [`AddrBus]	addr,
	input  wire [`DataBus]	d_in,
	input  wire 		we_,
	output wire [`DataBus]	d_out
);
	
	/******内部信号******/
	reg	[`DataBus]	ff[`DATA_D-1:0];
	integer			i;
	
	/******读取访问******/
	assign	d_out=ff[addr];				//读取数据与时钟无关。
	
	/******写入访问******/
	always	@(posedge clk or negedge reset_) begin

		if(reset_ == `ENABLE_)
			ff[i] <= #1 {`DATA_W{1'b0}};
		else if(we_ ==`ENABLE_)
			ff[addr] <= #1 d_in;
						end

endmodule

cpuother/regfile/regfile_test.v
`timescale 1ns/1ps
`include "regfile.h"

/******模块******/
module regfile_test;
	reg			clk;
	reg			reset_;	
	//访问接口
	reg	[`AddrBus]	addr;			//地址
	reg	[`DataBus]	d_in;			//输入数据
	reg			we_;			//使能信号
	wire	[`DataBus]	d_out;			//输出数据
	/******内部变量******/
	integer			i;
	/******仿真步长******/
	parameter		STEP = 100.000;		//10Mhz
	
	/*******生成时钟******/
	always #(STEP/2)	clk=~clk;
	
	/******实例化*******/
	regfile regfile(
		.clk	(clk),
		.reset_	(reset_),
		/******访问接口*********/
		.addr	(addr),
		.d_in	(d_in),
		.we_	(we_),
		.d_out	(d_out)
	);

	/***********测试用例************/
	initial begin
		/********初始化********/
		# 0 		
			clk	<= `HIGH;
			reset_ 	<= `ENABLE_;
			addr	<= {`ADDR_W{1'b0}};
			d_in	<= {`DATA_W{1'b0}};
			we_	<= `DISABLE_;
				
		# (STEP *3/4)					//延迟3/4
		# STEP		reset_	<= `DISABLE_;		//解除复位

		/********循环仿真******/
		# STEP 	
			for(i=0; i<`DATA_D;i=i+1) begin
			# STEP
				addr 	<= i;			//在地址i处写入
				d_in	<= i;
				we_	<= `ENABLE_;
			
			# STEP
				addr	<= {`ADDR_W{1'b0}};	//读取地址0
				d_in	<= {`DATA_W{1'b0}};
				we_	<= `DISABLE_;
				if(d_out == i)
					$display ($time,"ff[%d] Read/Write Check OK!",i);
				else
					$display ($time,"ff[%d] Read/Write Check NG!",i);
			end
		# STEP 
			$finish;
	end

	/*********输出波形**********/
	initial begin
		$dumpfile("regfile.vcd");
		$dumpvars(0,regfile);
	end
	

endmodule

cpuother/regfile/regfile.vcd
$date
	Fri Jul 08 14:28:19 2016
$end
$version
	Icarus Verilog
$end
$timescale
	1ps
$end
$scope module regfile_test $end
$scope module regfile $end
$var wire 5 ! addr [4:0] $end
$var wire 1 " clk $end
$var wire 32 # d_in [31:0] $end
$var wire 32 $ d_out [31:0] $end
$var wire 1 % reset_ $end
$var wire 1 & we_ $end
$var integer 32 ' i [31:0] $end
$upscope $end
$upscope $end
$enddefinitions $end
#0
$dumpvars
bx '
1&
0%
bx $
b0 #
1"
b0 !
$end
#50000
0"
#100000
1"
#150000
0"
#175000
1%
#200000
1"
#250000
0"
#300000
1"
#350000
0"
#374000
0&
#400000
1"
#401000
b0 $
#450000
0"
#474000
1&
#500000
1"
#550000
0"
#574000
0&
b1 #
bx $
b1 !
#600000
1"
#601000
b1 $
#650000
0"
#674000
1&
b0 #
b0 $
b0 !
#700000
1"
#750000
0"
#774000
0&
b10 #
bx $
b10 !
#800000
1"
#801000
b10 $
#850000
0"
#874000
1&
b0 #
b0 $
b0 !
#900000
1"
#950000
0"
#974000
0&
b11 #
bx $
b11 !
#1000000
1"
#1001000
b11 $
#1050000
0"
#1074000
1&
b0 #
b0 $
b0 !
#1100000
1"
#1150000
0"
#1174000
0&
b100 #
bx $
b100 !
#1200000
1"
#1201000
b100 $
#1250000
0"
#1274000
1&
b0 #
b0 $
b0 !
#1300000
1"
#1350000
0"
#1374000
0&
b101 #
bx $
b101 !
#1400000
1"
#1401000
b101 $
#1450000
0"
#1474000
1&
b0 #
b0 $
b0 !
#1500000
1"
#1550000
0"
#1574000
0&
b110 #
bx $
b110 !
#1600000
1"
#1601000
b110 $
#1650000
0"
#1674000
1&
b0 #
b0 $
b0 !
#1700000
1"
#1750000
0"
#1774000
0&
b111 #
bx $
b111 !
#1800000
1"
#1801000
b111 $
#1850000
0"
#1874000
1&
b0 #
b0 $
b0 !
#1900000
1"
#1950000
0"
#1974000
0&
b1000 #
bx $
b1000 !
#2000000
1"
#2001000
b1000 $
#2050000
0"
#2074000
1&
b0 #
b0 $
b0 !
#2100000
1"
#2150000
0"
#2174000
0&
b1001 #
bx $
b1001 !
#2200000
1"
#2201000
b1001 $
#2250000
0"
#2274000
1&
b0 #
b0 $
b0 !
#2300000
1"
#2350000
0"
#2374000
0&
b1010 #
bx $
b1010 !
#2400000
1"
#2401000
b1010 $
#2450000
0"
#2474000
1&
b0 #
b0 $
b0 !
#2500000
1"
#2550000
0"
#2574000
0&
b1011 #
bx $
b1011 !
#2600000
1"
#2601000
b1011 $
#2650000
0"
#2674000
1&
b0 #
b0 $
b0 !
#2700000
1"
#2750000
0"
#2774000
0&
b1100 #
bx $
b1100 !
#2800000
1"
#2801000
b1100 $
#2850000
0"
#2874000
1&
b0 #
b0 $
b0 !
#2900000
1"
#2950000
0"
#2974000
0&
b1101 #
bx $
b1101 !
#3000000
1"
#3001000
b1101 $
#3050000
0"
#3074000
1&
b0 #
b0 $
b0 !
#3100000
1"
#3150000
0"
#3174000
0&
b1110 #
bx $
b1110 !
#3200000
1"
#3201000
b1110 $
#3250000
0"
#3274000
1&
b0 #
b0 $
b0 !
#3300000
1"
#3350000
0"
#3374000
0&
b1111 #
bx $
b1111 !
#3400000
1"
#3401000
b1111 $
#3450000
0"
#3474000
1&
b0 #
b0 $
b0 !
#3500000
1"
#3550000
0"
#3574000
0&
b10000 #
bx $
b10000 !
#3600000
1"
#3601000
b10000 $
#3650000
0"
#3674000
1&
b0 #
b0 $
b0 !
#3700000
1"
#3750000
0"
#3774000
0&
b10001 #
bx $
b10001 !
#3800000
1"
#3801000
b10001 $
#3850000
0"
#3874000
1&
b0 #
b0 $
b0 !
#3900000
1"
#3950000
0"
#3974000
0&
b10010 #
bx $
b10010 !
#4000000
1"
#4001000
b10010 $
#4050000
0"
#4074000
1&
b0 #
b0 $
b0 !
#4100000
1"
#4150000
0"
#4174000
0&
b10011 #
bx $
b10011 !
#4200000
1"
#4201000
b10011 $
#4250000
0"
#4274000
1&
b0 #
b0 $
b0 !
#4300000
1"
#4350000
0"
#4374000
0&
b10100 #
bx $
b10100 !
#4400000
1"
#4401000
b10100 $
#4450000
0"
#4474000
1&
b0 #
b0 $
b0 !
#4500000
1"
#4550000
0"
#4574000
0&
b10101 #
bx $
b10101 !
#4600000
1"
#4601000
b10101 $
#4650000
0"
#4674000
1&
b0 #
b0 $
b0 !
#4700000
1"
#4750000
0"
#4774000
0&
b10110 #
bx $
b10110 !
#4800000
1"
#4801000
b10110 $
#4850000
0"
#4874000
1&
b0 #
b0 $
b0 !
#4900000
1"
#4950000
0"
#4974000
0&
b10111 #
bx $
b10111 !
#5000000
1"
#5001000
b10111 $
#5050000
0"
#5074000
1&
b0 #
b0 $
b0 !
#5100000
1"
#5150000
0"
#5174000
0&
b11000 #
bx $
b11000 !
#5200000
1"
#5201000
b11000 $
#5250000
0"
#5274000
1&
b0 #
b0 $
b0 !
#5300000
1"
#5350000
0"
#5374000
0&
b11001 #
bx $
b11001 !
#5400000
1"
#5401000
b11001 $
#5450000
0"
#5474000
1&
b0 #
b0 $
b0 !
#5500000
1"
#5550000
0"
#5574000
0&
b11010 #
bx $
b11010 !
#5600000
1"
#5601000
b11010 $
#5650000
0"
#5674000
1&
b0 #
b0 $
b0 !
#5700000
1"
#5750000
0"
#5774000
0&
b11011 #
bx $
b11011 !
#5800000
1"
#5801000
b11011 $
#5850000
0"
#5874000
1&
b0 #
b0 $
b0 !
#5900000
1"
#5950000
0"
#5974000
0&
b11100 #
bx $
b11100 !
#6000000
1"
#6001000
b11100 $
#6050000
0"
#6074000
1&
b0 #
b0 $
b0 !
#6100000
1"
#6150000
0"
#6174000
0&
b11101 #
bx $
b11101 !
#6200000
1"
#6201000
b11101 $
#6250000
0"
#6274000
1&
b0 #
b0 $
b0 !
#6300000
1"
#6350000
0"
#6374000
0&
b11110 #
bx $
b11110 !
#6400000
1"
#6401000
b11110 $
#6450000
0"
#6474000
1&
b0 #
b0 $
b0 !
#6500000
1"
#6550000
0"
#6574000
0&
b11111 #
bx $
b11111 !
#6600000
1"
#6601000
b11111 $
#6650000
0"
#6674000
1&
b0 #
b0 $
b0 !
